<?xml version="1.0" encoding="utf-8"?>
<abapGit version="v1.0.0" serializer="LCL_OBJECT_WEBI" serializer_version="v1.0.0">
 <asx:abap xmlns:asx="http://www.sap.com/abapxml" version="1.0">
  <asx:values>
   <WEBI>
    <VEPTEXT>web service trial</VEPTEXT>
    <PVEPHEADER>
     <VEPHEADER>
      <VEPNAME>ZDOP_WS_1</VEPNAME>
      <VERSION>A</VERSION>
      <VEPNAMEEXT>zdop_ws_1</VEPNAMEEXT>
     </VEPHEADER>
    </PVEPHEADER>
    <PVEPFUNCTION>
     <VEPFUNCTION>
      <VEPNAME>ZDOP_WS_1</VEPNAME>
      <VERSION>A</VERSION>
      <FUNCTION>ZDOP_WS</FUNCTION>
      <MAPPEDNAME>ZDOP_WS</MAPPEDNAME>
      <IS_EXPOSED>X</IS_EXPOSED>
     </VEPFUNCTION>
    </PVEPFUNCTION>
    <PVEPPARAMETER>
     <VEPPARAMETER>
      <VEPNAME>ZDOP_WS_1</VEPNAME>
      <VERSION>A</VERSION>
      <FUNCTION>ZDOP_WS</FUNCTION>
      <VEPPARAM>I_NUM2</VEPPARAM>
      <VEPPARAMTYPE>I</VEPPARAMTYPE>
      <MAPPEDNAME>I_NUM2</MAPPEDNAME>
      <IS_EXPOSED>X</IS_EXPOSED>
      <IS_INITIAL>X</IS_INITIAL>
      <TYPENAME>INT4</TYPENAME>
     </VEPPARAMETER>
     <VEPPARAMETER>
      <VEPNAME>ZDOP_WS_1</VEPNAME>
      <VERSION>A</VERSION>
      <FUNCTION>ZDOP_WS</FUNCTION>
      <VEPPARAM>I_NUM1</VEPPARAM>
      <VEPPARAMTYPE>I</VEPPARAMTYPE>
      <MAPPEDNAME>I_NUM1</MAPPEDNAME>
      <IS_EXPOSED>X</IS_EXPOSED>
      <IS_INITIAL>X</IS_INITIAL>
      <TYPENAME>INT4</TYPENAME>
     </VEPPARAMETER>
     <VEPPARAMETER>
      <VEPNAME>ZDOP_WS_1</VEPNAME>
      <VERSION>A</VERSION>
      <FUNCTION>ZDOP_WS</FUNCTION>
      <VEPPARAM>E_RESULT</VEPPARAM>
      <VEPPARAMTYPE>O</VEPPARAMTYPE>
      <MAPPEDNAME>E_RESULT</MAPPEDNAME>
      <IS_EXPOSED>X</IS_EXPOSED>
      <IS_INITIAL>X</IS_INITIAL>
      <TYPENAME>INT4</TYPENAME>
     </VEPPARAMETER>
    </PVEPPARAMETER>
    <PVEPTYPE>
     <VEPTYPE>
      <VEPNAME>ZDOP_WS_1</VEPNAME>
      <VERSION>A</VERSION>
      <TYPENAME>INT4</TYPENAME>
      <TYPE>E</TYPE>
     </VEPTYPE>
    </PVEPTYPE>
    <PVEPELEMTYPE>
     <VEPELEMTYPE>
      <VEPNAME>ZDOP_WS_1</VEPNAME>
      <VERSION>A</VERSION>
      <TYPENAME>INT4</TYPENAME>
      <KIND>DTEL</KIND>
      <BUILD_IN_TYPE>INT4</BUILD_IN_TYPE>
      <LENGTH>10</LENGTH>
      <SIGNED>X</SIGNED>
      <ABAPTYPE>I</ABAPTYPE>
     </VEPELEMTYPE>
    </PVEPELEMTYPE>
    <PVEPTYPESOAPEXT>
     <VEPTYPESOAPEXT>
      <VEPNAME>ZDOP_WS_1</VEPNAME>
      <VERSION>A</VERSION>
      <TYPENAME>INT4</TYPENAME>
      <NAMESPACE>urn:sap-com:document:sap:rfc:functions</NAMESPACE>
     </VEPTYPESOAPEXT>
    </PVEPTYPESOAPEXT>
    <PVEPFUNCSOAPEXT>
     <VEPFUNCSOAPEXT>
      <VEPNAME>ZDOP_WS_1</VEPNAME>
      <VERSION>A</VERSION>
      <FUNCTION>ZDOP_WS</FUNCTION>
      <NAMESPACE>urn:sap-com:document:sap:rfc:functions</NAMESPACE>
      <RESPONSENAME>ZDOP_WSResponse</RESPONSENAME>
      <REQUESTNAME>ZDOP_WS</REQUESTNAME>
     </VEPFUNCSOAPEXT>
    </PVEPFUNCSOAPEXT>
    <PVEPFIELDREF>
     <VEPFIELDREF>
      <VEPNAME>ZDOP_WS_1</VEPNAME>
      <VERSION>A</VERSION>
      <FUNCTION>ZDOP_WS</FUNCTION>
      <VEPPARAM>I_NUM2</VEPPARAM>
      <VEPPARAMTYPE>I</VEPPARAMTYPE>
      <FIELDNAME>I_NUM2</FIELDNAME>
      <SUBSTRUCID>0000000001</SUBSTRUCID>
      <TYPE>E</TYPE>
      <TYPENAME>INT4</TYPENAME>
     </VEPFIELDREF>
     <VEPFIELDREF>
      <VEPNAME>ZDOP_WS_1</VEPNAME>
      <VERSION>A</VERSION>
      <FUNCTION>ZDOP_WS</FUNCTION>
      <VEPPARAM>I_NUM1</VEPPARAM>
      <VEPPARAMTYPE>I</VEPPARAMTYPE>
      <FIELDNAME>I_NUM1</FIELDNAME>
      <SUBSTRUCID>0000000001</SUBSTRUCID>
      <TYPE>E</TYPE>
      <TYPENAME>INT4</TYPENAME>
     </VEPFIELDREF>
     <VEPFIELDREF>
      <VEPNAME>ZDOP_WS_1</VEPNAME>
      <VERSION>A</VERSION>
      <FUNCTION>ZDOP_WS</FUNCTION>
      <VEPPARAM>E_RESULT</VEPPARAM>
      <VEPPARAMTYPE>O</VEPPARAMTYPE>
      <FIELDNAME>E_RESULT</FIELDNAME>
      <SUBSTRUCID>0000000001</SUBSTRUCID>
      <TYPE>E</TYPE>
      <TYPENAME>INT4</TYPENAME>
     </VEPFIELDREF>
    </PVEPFIELDREF>
    <PVEPENDPOINT>
     <VEPENDPOINT>
      <RELID>VI</RELID>
      <VEPNAME>ZDOP_WS_1</VEPNAME>
      <VERSION>A</VERSION>
      <ENDPOINTTYPE>FUNC</ENDPOINTTYPE>
      <DATA_VERSION>1</DATA_VERSION>
      <DEF_START_PT>I</DEF_START_PT>
      <ENDPOINTNAME>ZDOP_WS</ENDPOINTNAME>
      <CLUSTR>101</CLUSTR>
     </VEPENDPOINT>
    </PVEPENDPOINT>
    <PVEPVISOAPEXT>
     <VEPVISOAPEXT>
      <VEPNAME>ZDOP_WS_1</VEPNAME>
      <VERSION>A</VERSION>
      <NAMESPACE>urn:sap-com:document:sap:rfc:functions</NAMESPACE>
      <SOAP_APPL_URI>urn:sap-com:soap:runtime:application:rfc:710</SOAP_APPL_URI>
     </VEPVISOAPEXT>
    </PVEPVISOAPEXT>
    <PWSHEADER>
     <WSHEADER>
      <WSNAME>ZDOP_WS_1</WSNAME>
      <VERSION>A</VERSION>
      <WSNAMEEXT>zdop_ws_1</WSNAMEEXT>
      <PREFIX>/sap/bc/srt/rfc/sap/</PREFIX>
      <VINAME>ZDOP_WS_1</VINAME>
     </WSHEADER>
    </PWSHEADER>
    <PWSSOAPPROP>
     <WSSOAPPROP>
      <WSNAME>ZDOP_WS_1</WSNAME>
      <VERSION>A</VERSION>
      <FEATURE>http://www.sap.com/NW05/soap/features/blocking/</FEATURE>
      <SOAPAPP>FUNC</SOAPAPP>
      <FUNCREF>ZDOP_WS</FUNCREF>
      <PROPNUM>0001</PROPNUM>
      <PROPNAME>enableBlocking</PROPNAME>
      <VALUE>true</VALUE>
      <PROFILE_URI>PRF_DT_OP_COM_SYNC</PROFILE_URI>
     </WSSOAPPROP>
     <WSSOAPPROP>
      <WSNAME>ZDOP_WS_1</WSNAME>
      <VERSION>A</VERSION>
      <FEATURE>http://www.sap.com/NW05/soap/features/commit/</FEATURE>
      <SOAPAPP>FUNC</SOAPAPP>
      <FUNCREF>ZDOP_WS</FUNCREF>
      <PROPNUM>0001</PROPNUM>
      <PROPNAME>enableCommit</PROPNAME>
      <VALUE>false</VALUE>
      <PROFILE_URI>PRF_DT_OP_COM_SYNC</PROFILE_URI>
     </WSSOAPPROP>
     <WSSOAPPROP>
      <WSNAME>ZDOP_WS_1</WSNAME>
      <VERSION>A</VERSION>
      <FEATURE>http://www.sap.com/NW05/soap/features/transaction/</FEATURE>
      <SOAPAPP>FUNC</SOAPAPP>
      <FUNCREF>ZDOP_WS</FUNCREF>
      <PROPNUM>0001</PROPNUM>
      <PROPNAME>required</PROPNAME>
      <VALUE>no</VALUE>
      <PROFILE_URI>PRF_DT_OP_COM_SYNC</PROFILE_URI>
     </WSSOAPPROP>
     <WSSOAPPROP>
      <WSNAME>ZDOP_WS_1</WSNAME>
      <VERSION>A</VERSION>
      <FEATURE>http://www.sap.com/NW05/soap/features/wsrm/</FEATURE>
      <SOAPAPP>FUNC</SOAPAPP>
      <FUNCREF>ZDOP_WS</FUNCREF>
      <PROPNUM>0001</PROPNUM>
      <PROPNAME>enableWSRM</PROPNAME>
      <VALUE>false</VALUE>
      <PROFILE_URI>PRF_DT_OP_COM_SYNC</PROFILE_URI>
     </WSSOAPPROP>
     <WSSOAPPROP>
      <WSNAME>ZDOP_WS_1</WSNAME>
      <VERSION>A</VERSION>
      <FEATURE>http://www.sap.com/esi/NW05/rif/</FEATURE>
      <SOAPAPP>FUNC</SOAPAPP>
      <FUNCREF>ZDOP_WS</FUNCREF>
      <PROPNUM>0001</PROPNUM>
      <PROPNAME>mep</PROPNAME>
      <VALUE>RequestResponse</VALUE>
      <PROFILE_URI>PRF_DT_OP_COM_SYNC</PROFILE_URI>
     </WSSOAPPROP>
     <WSSOAPPROP>
      <WSNAME>ZDOP_WS_1</WSNAME>
      <VERSION>A</VERSION>
      <FEATURE>http://www.sap.com/webas/630/soap/features/authentication/</FEATURE>
      <SOAPAPP>FUNC</SOAPAPP>
      <PROPNUM>0001</PROPNUM>
      <PROPNAME>AuthenticationLevel</PROPNAME>
      <VALUE>None</VALUE>
      <PROFILE_URI>PRF_DT_IF_SEC_NO</PROFILE_URI>
     </WSSOAPPROP>
     <WSSOAPPROP>
      <WSNAME>ZDOP_WS_1</WSNAME>
      <VERSION>A</VERSION>
      <FEATURE>http://www.sap.com/webas/630/soap/features/session/</FEATURE>
      <SOAPAPP>FUNC</SOAPAPP>
      <PROPNUM>0001</PROPNUM>
      <PROPNAME>enableSession</PROPNAME>
      <VALUE>false</VALUE>
      <PROFILE_URI>PRF_DT_IF_COM_STATELESS</PROFILE_URI>
     </WSSOAPPROP>
     <WSSOAPPROP>
      <WSNAME>ZDOP_WS_1</WSNAME>
      <VERSION>A</VERSION>
      <FEATURE>http://www.sap.com/webas/630/soap/features/transportguarantee/</FEATURE>
      <SOAPAPP>FUNC</SOAPAPP>
      <PROPNUM>0001</PROPNUM>
      <PROPNAME>Level</PROPNAME>
      <VALUE>None</VALUE>
      <PROFILE_URI>PRF_DT_IF_SEC_NO</PROFILE_URI>
     </WSSOAPPROP>
     <WSSOAPPROP>
      <WSNAME>ZDOP_WS_1</WSNAME>
      <VERSION>A</VERSION>
      <FEATURE>http://www.sap.com/webas/640/soap/features/messageId/</FEATURE>
      <SOAPAPP>FUNC</SOAPAPP>
      <PROPNUM>0001</PROPNUM>
      <PROPNAME>enableMessageId</PROPNAME>
      <VALUE>true</VALUE>
      <PROFILE_URI>PRF_DT_IF_COM_STATELESS</PROFILE_URI>
     </WSSOAPPROP>
    </PWSSOAPPROP>
   </WEBI>
   <SOTR>
    <item>
     <HEADER>
      <CONCEPT>000C2940A6BB1EDC95CE398AE892D64D</CONCEPT>
      <CREA_LAN>T</CREA_LAN>
      <TRALA_TYPE>1</TRALA_TYPE>
      <OBJID_VEC>AAg=</OBJID_VEC>
     </HEADER>
     <ENTRIES>
      <SOTR_TEXT>
       <CONCEPT>000C2940A6BB1EDC95CE398AE892D64D</CONCEPT>
       <LANGU>T</LANGU>
       <LFD_NUM>0001</LFD_NUM>
       <FLAG_CNTXT>X</FLAG_CNTXT>
       <STATUS>R</STATUS>
       <LENGTH>027</LENGTH>
       <TEXT>web service trial</TEXT>
      </SOTR_TEXT>
     </ENTRIES>
    </item>
   </SOTR>
   <SOTR_USE>
    <SOTR_USE>
     <PGMID>R3TR</PGMID>
     <OBJECT>WEBI</OBJECT>
     <OBJ_NAME>ZDOP_WS_1</OBJ_NAME>
     <CONCEPT>000C2940A6BB1EDC95CE398AE892D64D</CONCEPT>
     <LFD_NUM>0001</LFD_NUM>
    </SOTR_USE>
   </SOTR_USE>
  </asx:values>
 </asx:abap>
</abapGit>
